Metadata-Version: 2.1
Name: chat-manager-api
Version: 1.0.0
Summary: Chat Manager API wrapper
Home-page: https://github.com/lordralinc/chat_manager_api
Author: lordralinc
License: MIT
Platform: UNKNOWN
Classifier: Programming Language :: Python :: 3.7
Classifier: Programming Language :: Python :: 3.8
Classifier: Programming Language :: Python :: 3.9
Classifier: Operating System :: OS Independent
